figlinq/__init__.py
figlinq/config.py
figlinq/exceptions.py
figlinq/files.py
figlinq/session.py
figlinq/tools.py
figlinq/utils.py
figlinq/analysis/__init__.py
figlinq/analysis/payloads.py
figlinq/analysis/schemas.py
figlinq/api/__init__.py
figlinq/api/utils.py
figlinq/api/v2/__init__.py
figlinq/api/v2/analysis.py
figlinq/api/v2/dash_apps.py
figlinq/api/v2/dashboards.py
figlinq/api/v2/external_files.py
figlinq/api/v2/external_images.py
figlinq/api/v2/files.py
figlinq/api/v2/folders.py
figlinq/api/v2/grids.py
figlinq/api/v2/html_text.py
figlinq/api/v2/images.py
figlinq/api/v2/jupyter_notebooks.py
figlinq/api/v2/plot_schema.py
figlinq/api/v2/plots.py
figlinq/api/v2/spectacle_presentations.py
figlinq/api/v2/users.py
figlinq/api/v2/utils.py
figlinq/dashboard_objs/__init__.py
figlinq/dashboard_objs/dashboard_objs.py
figlinq/figlinq/__init__.py
figlinq/figlinq/figlinq.py
figlinq/grid_objs/__init__.py
figlinq/grid_objs/grid_objs.py
figlinq/plotly/__init__.py
figlinq/plotly/plotly.py
figlinq/presentation_objs/__init__.py
figlinq/presentation_objs/presentation_objs.py
figlinq/templates/figlinq-modern.json
figlinq-0.2.32.dist-info/METADATA
figlinq-0.2.32.dist-info/WHEEL
figlinq-0.2.32.dist-info/top_level.txt
figlinq-0.2.32.dist-info/RECORD
